dude/__init__.py
dude/base.py
dude/context.py
dude/optional/__init__.py
dude/optional/beautifulsoup_scraper.py
dude/optional/lxml_scraper.py
dude/optional/parsel_scraper.py
dude/optional/selenium_scraper.py
dude/optional/utils.py
dude/playwright_scraper.py
dude/rule.py
dude/scraped_data.py
dude/scraper.py
dude/storage.py
pydude-0.28.0.dist-info/LICENSE
pydude-0.28.0.dist-info/METADATA
pydude-0.28.0.dist-info/WHEEL
pydude-0.28.0.dist-info/entry_points.txt
pydude-0.28.0.dist-info/RECORD
