Metadata-Version: 2.1
Name: pydude
Version: 0.28.0
Summary: dude uncomplicated data extraction
Home-page: https://github.com/roniemartinez/dude
License: AGPL-3.0-or-later
Keywords: scraping
Author: Ronie Martinez
Author-email: ronmarti18@gmail.com
Requires-Python: >=3.8.1,<4.0.0
Classifier: Development Status :: 2 - Pre-Alpha
Classifier: License :: OSI Approved :: GNU Affero General Public License v3 or later (AGPLv3+)
Classifier: Programming Language :: Python :: 3
Classifier: Programming Language :: Python :: 3.9
Classifier: Programming Language :: Python :: 3.10
Classifier: Programming Language :: Python :: 3.11
Classifier: Programming Language :: Python :: 3.12
Classifier: Programming Language :: Python :: 3.8
Classifier: Programming Language :: Python :: Implementation :: CPython
Classifier: Topic :: Software Development :: Libraries :: Python Modules
Provides-Extra: bs4
Provides-Extra: lxml
Provides-Extra: parsel
Provides-Extra: selenium
Requires-Dist: PyYAML (>=6.0,<7.0)
Requires-Dist: beautifulsoup4 (>=4.11.2,<5.0.0) ; extra == "bs4"
Requires-Dist: braveblock (>=0.5.0,<0.6.0)
Requires-Dist: cssselect (>=1.1.0,<2.0.0) ; extra == "lxml"
Requires-Dist: httpx (>=0.23.3,<0.28.0) ; extra == "bs4" or extra == "lxml" or extra == "parsel"
Requires-Dist: lxml (>=4.9.2,<6.0.0) ; extra == "lxml"
Requires-Dist: parsel (>=1.6.0,<1.7.0) ; extra == "parsel"
Requires-Dist: playwright (>=1.30.0,<2.0.0)
Requires-Dist: pybrowsers (>=0.4.1,<0.6.0) ; extra == "selenium"
Requires-Dist: selenium-wire (>=4.6.2,<6.0.0) ; extra == "selenium"
Requires-Dist: webdriver-manager (>=3.7,<5.0) ; extra == "selenium"
Project-URL: Documentation, https://roniemartinez.github.io/dude/
Project-URL: Donate, https://github.com/sponsors/roniemartinez
Project-URL: Repository, https://github.com/roniemartinez/dude
